odoo/addons/sale_timesheet_existing_project/README.rst
odoo/addons/sale_timesheet_existing_project/__init__.py
odoo/addons/sale_timesheet_existing_project/__manifest__.py
odoo/addons/sale_timesheet_existing_project/i18n/es.po
odoo/addons/sale_timesheet_existing_project/i18n/fr.po
odoo/addons/sale_timesheet_existing_project/i18n/it.po
odoo/addons/sale_timesheet_existing_project/i18n/sale_timesheet_existing_project.pot
odoo/addons/sale_timesheet_existing_project/models/__init__.py
odoo/addons/sale_timesheet_existing_project/models/product_product.py
odoo/addons/sale_timesheet_existing_project/models/product_template.py
odoo/addons/sale_timesheet_existing_project/models/sale_order.py
odoo/addons/sale_timesheet_existing_project/readme/CONFIGURE.rst
odoo/addons/sale_timesheet_existing_project/readme/DESCRIPTION.rst
odoo/addons/sale_timesheet_existing_project/readme/ROADMAP.rst
odoo/addons/sale_timesheet_existing_project/readme/USAGE.rst
odoo/addons/sale_timesheet_existing_project/static/description/icon.png
odoo/addons/sale_timesheet_existing_project/static/description/index.html
odoo/addons/sale_timesheet_existing_project/tests/__init__.py
odoo/addons/sale_timesheet_existing_project/tests/test_sale_timesheet_existing_project.py
odoo/addons/sale_timesheet_existing_project/views/product_template_views.xml
odoo/addons/sale_timesheet_existing_project/views/sale_order_views.xml
odoo12_addon_sale_timesheet_existing_project-12.0.1.0.0.99.dev11.dist-info/METADATA
odoo12_addon_sale_timesheet_existing_project-12.0.1.0.0.99.dev11.dist-info/WHEEL
odoo12_addon_sale_timesheet_existing_project-12.0.1.0.0.99.dev11.dist-info/top_level.txt
odoo12_addon_sale_timesheet_existing_project-12.0.1.0.0.99.dev11.dist-info/RECORD
